archerdfu/glyphs/__init__.py
archerdfu/glyphs/__main__.py
archerdfu/glyphs/caliber.py
archerdfu/glyphs/glyphs.py
archerdfu/glyphs/assets/cyrillic_ukraine.bmp
archerdfu/glyphs/assets/latin_v7.bmp
archerdfu/glyphs/assets/pictogram_v33.bmp
archerdfu/glyphs/assets/pictogram_v35_3_Seven.bmp
archerdfu/glyphs/assets/profimage.bmp
archerdfu/glyphs/fonts/cyrillic_ukraine.bin
archerdfu/glyphs/fonts/default.flf
archerdfu/glyphs/fonts/latin_v7.bin
archerdfu/glyphs/fonts/pictogram_v33.bin
archerdfu/glyphs/fonts/pictogram_v35_3_Seven.bin
archerdfu/glyphs/fonts/profimage.bin
archerdfu_glyphs-0.1.0b1.dist-info/METADATA
archerdfu_glyphs-0.1.0b1.dist-info/WHEEL
archerdfu_glyphs-0.1.0b1.dist-info/top_level.txt
archerdfu_glyphs-0.1.0b1.dist-info/RECORD
