Metadata-Version: 2.2
Name: archerdfu.glyphs
Version: 0.1.0b1
Summary: Module to operate and modify archer reticle2 files
License:                    GNU LESSER GENERAL PUBLIC LICENSE
Project-URL: Homepage, https://github.com/archerdfu/archerdfu.fonts
Project-URL: Bug Reports, https://github.com/archerdfu/archerdfu.fonts/issues
Project-URL: Source, https://github.com/archerdfu/archerdfu.fonts
Keywords: ARCHER,archerdfu,pydfuutil,dfuutil
Classifier: Intended Audience :: Developers
Classifier: Natural Language :: English
Classifier: Programming Language :: Python
Classifier: Topic :: Software Development :: Libraries :: Python Modules
Classifier: Programming Language :: Python :: 3
Classifier: Programming Language :: Python :: 3 :: Only
Classifier: Programming Language :: Python :: 3.10
Classifier: Programming Language :: Python :: 3.11
Classifier: Programming Language :: Python :: 3.12
Classifier: Programming Language :: Python :: Implementation :: CPython
Requires-Python: >=3.10
Requires-Dist: pillow>=11.1.0
Requires-Dist: pyfiglet>=1.0.2
Requires-Dist: typing-extensions>=4.12.2
Provides-Extra: dev
Requires-Dist: pytest>=8.3.5; extra == "dev"
